django_cal/__init__.py
django_cal/views.py
django_cal-0.4.2.dist-info/METADATA
django_cal-0.4.2.dist-info/WHEEL
django_cal-0.4.2.dist-info/licenses/AUTHORS.md
django_cal-0.4.2.dist-info/licenses/LICENSE
django_cal-0.4.2.dist-info/RECORD
