Metadata-Version: 2.1
Name: django-cal
Version: 0.4.2
Summary: Django app to enable exporting of events to iCalendar files.
Project-URL: Homepage, https://github.com/statesofpop/django-cal/
Project-URL: Bug Tracker, https://github.com/statesofpop/django-cal/issues
Author-email: Maik Hoepfel <m@maikhoepfel.de>
License: Copyright (c) statesofpop and individual contributors.
License-File: AUTHORS.md
License-File: LICENSE
Classifier: Development Status :: 5 - Production/Stable
Classifier: Framework :: Django
Classifier: Intended Audience :: Developers
Classifier: License :: OSI Approved :: BSD License
Classifier: Operating System :: OS Independent
Classifier: Programming Language :: Python
Classifier: Programming Language :: Python :: 3
Requires-Python: >=3.7
Requires-Dist: python-dateutil
Requires-Dist: vobject
Provides-Extra: tests
Requires-Dist: black; extra == 'tests'
Requires-Dist: bumpver; extra == 'tests'
Requires-Dist: flake8; extra == 'tests'
Requires-Dist: isort; extra == 'tests'
Requires-Dist: pre-commit; extra == 'tests'
Requires-Dist: pytest; extra == 'tests'
Requires-Dist: pytest-django; extra == 'tests'
Requires-Dist: pyupgrade; extra == 'tests'
